flake8_forbidden_func/__init__.py
flake8_forbidden_func/__version__.py
flake8_forbidden_func/ast_tools.py
flake8_forbidden_func/checker.py
flake8_forbidden_func/custom_types.py
flake8_forbidden_func/parser.py
flake8_forbidden_func/pathes.py
flake8_forbidden_func/rules.py
tests/__init__.py
tests/conftest.py
tests/test_integration/__init__.py
tests/test_integration/test_cheker.py
tests/test_unit/__init__.py
tests/test_unit/test_ast_tools.py
tests/test_unit/test_checker.py
tests/test_unit/test_parser.py
tests/test_unit/test_rules.py
flake8_forbidden_func-0.1.0.dist-info/LICENSE
flake8_forbidden_func-0.1.0.dist-info/METADATA
flake8_forbidden_func-0.1.0.dist-info/WHEEL
flake8_forbidden_func-0.1.0.dist-info/entry_points.txt
flake8_forbidden_func-0.1.0.dist-info/top_level.txt
flake8_forbidden_func-0.1.0.dist-info/RECORD
