Metadata-Version: 2.1
Name: flake8-forbidden-func
Version: 0.1.0
Summary: An extension for flake8 that forbids some functions in some modules.
Home-page: https://github.com/tripcher/flake8-forbidden-func
Author: Stanislav Shkitin
Author-email: stanislav.shkitin@yandex.ru
License: MIT
Keywords: flake8
Classifier: Environment :: Console
Classifier: Framework :: Flake8
Classifier: Operating System :: OS Independent
Classifier: Topic :: Software Development :: Documentation
Classifier: Topic :: Software Development :: Libraries :: Python Modules
Classifier: Topic :: Software Development :: Quality Assurance
Classifier: Programming Language :: Python
Classifier: Programming Language :: Python :: 3.7
Classifier: Programming Language :: Python :: 3.8
Classifier: Programming Language :: Python :: 3.9
Classifier: Programming Language :: Python :: 3.10
Requires-Python: >=3.7
License-File: LICENSE
Requires-Dist: setuptools
